{
  "id": "quiz-1",
  "questions": [
    {
      "id": "q1",
      "title": "Capital of France?",
      "choices": [
        "Paris",
        "London",
        "Rome"
      ],
      "goodChoice": "Paris",
      "points": 10
    },
    {
      "id": "q2",
      "title": "2+2",
      "choices": [
        "2",
        "4",
        "5"
      ],
      "goodChoice": "4",
      "points": 50
    }
  ],
  "players": [
    {
      "id": "cb4559cc-e4e5-4869-87b3-db1c02b40013",
      "name": "Linna",
      "answers": [
        {
          "id": "f340ccc4-a837-42bf-9f83-57210a19d842",
          "questionId": "q1",
          "answerChoice": "Paris"
        },
        {
          "id": "25a036f8-29f5-4190-b3ea-dcb75d2606e6",
          "questionId": "q2",
          "answerChoice": "4"
        }
      ]
    },
    {
      "id": "79356f43-1a3c-4859-aa75-1d259cb63298",
      "name": "Liza",
      "answers": [
        {
          "id": "76e6f10e-a53f-4f91-af31-061489bdb365",
          "questionId": "q1",
          "answerChoice": ""
        },
        {
          "id": "88f52aaa-8b78-437a-8ca1-ab7e88d8f004",
          "questionId": "q2",
          "answerChoice": ""
        }
      ]
    },
    {
      "id": "b2782dc3-55fc-49c8-92b4-4019163697db",
      "name": "Veysean",
      "answers": [
        {
          "id": "86df4119-04ac-4927-831a-c8b0b02982d1",
          "questionId": "q1",
          "answerChoice": "London"
        },
        {
          "id": "62ab147f-7c4a-4f7b-966d-5afbe720365b",
          "questionId": "q2",
          "answerChoice": "4"
        }
      ]
    },
    {
      "id": "4f2586f2-6d4e-40ef-9d76-9346b624783d",
      "name": "Nika",
      "answers": [
        {
          "id": "9f532042-a1f5-4940-88d9-4dc1210c912f",
          "questionId": "q1",
          "answerChoice": "Rome"
        },
        {
          "id": "3943a59a-fa43-437f-a7eb-97578b2597c7",
          "questionId": "q2",
          "answerChoice": "2"
        }
      ]
    },
    {
      "id": "847b1be4-d145-4b55-a51b-14a3ab85b0e2",
      "name": "Gechty",
      "answers": [
        {
          "id": "a34f8f1b-37e9-411e-9dfc-47ca775cf818",
          "questionId": "q1",
          "answerChoice": ""
        },
        {
          "id": "c6ce7b2d-42f3-4849-9c0e-33e02a18aff5",
          "questionId": "q2",
          "answerChoice": "4"
        }
      ]
    },
    {
      "id": "eecf7dc2-5e62-4afe-bcef-df98affe691e",
      "name": "Sivmey",
      "answers": [
        {
          "id": "e24dee61-9ca0-4149-a074-443f93c63621",
          "questionId": "q1",
          "answerChoice": "PAris"
        },
        {
          "id": "48e0343c-b247-4e6c-9c86-e742d96a51f3",
          "questionId": "q2",
          "answerChoice": "4"
        }
      ]
    },
    {
      "id": "e2c1acb3-66b3-421e-814b-6f4878035725",
      "name": "dhckjdc",
      "answers": [
        {
          "id": "735001e0-7577-47b4-81a8-6fa19a148b9d",
          "questionId": "q1",
          "answerChoice": "Paris"
        },
        {
          "id": "1fdb2ac9-0cc1-44b9-bd38-dd3d32099450",
          "questionId": "q2",
          "answerChoice": "4"
        }
      ]
    }
  ]
}